{"cameraMode":{"drawMode":0,"name":"Shaded","section":"Shading Mode"},"sceneLighting":true,"audioPlay":false,"sceneViewState":{"showFog":true,"showMaterialUpdate":false,"showSkybox":true,"showFlares":true,"showImageEffects":true,"showParticleSystems":true},"in2DMode":false,"pivot":{"x":34.580780029296878,"y":385.73040771484377,"z":53.81647491455078},"rotation":{"x":0.15349869430065156,"y":0.6862921714782715,"z":-0.15166765451431275,"w":0.694577157497406},"size":92.59912109375,"orthographic":false}